random_nick_generator/__init__.py
random_nick_generator/generator.py
random_nick_generator-0.3.dist-info/METADATA
random_nick_generator-0.3.dist-info/WHEEL
random_nick_generator-0.3.dist-info/top_level.txt
random_nick_generator-0.3.dist-info/RECORD
