Metadata-Version: 2.1
Name: random-nick-generator
Version: 0.3
Summary: A simple library to generate random nicknames.
Home-page: https://github.com/dsadasdasdsaas/random-nick-generator
Author: vsenikzianyati
Author-email: fmsg4341@gmail.com
